cleanback/__init__.py
cleanback/__main__.py
cleanback-1.3.0.dist-info/licenses/LICENSE
cleanback-1.3.0.dist-info/METADATA
cleanback-1.3.0.dist-info/WHEEL
cleanback-1.3.0.dist-info/entry_points.txt
cleanback-1.3.0.dist-info/top_level.txt
cleanback-1.3.0.dist-info/RECORD
