Metadata-Version: 2.4
Name: cleanback
Version: 1.3.0
Summary: Cleanup Failed Docker Backups — parallel validator (using dirval)
Author-email: Kevin Veen-Birkenbach <kevin@veen.world>
License:                     GNU AFFERO GENERAL PUBLIC LICENSE
Project-URL: Homepage, https://github.com/kevinveenbirkenbach/cleanup-failed-backups
Project-URL: Repository, https://github.com/kevinveenbirkenbach/cleanup-failed-backups
Keywords: backup,docker,validation,cleanup,dirval
Requires-Python: >=3.8
License-File: LICENSE
Requires-Dist: dirval>=0.1.0
Dynamic: license-file
